{
	"name": "Event_Sheet_Functions",
	"events": [
		{
			"functionName": "EnergyBarRefresh",
			"functionDescription": "Display Fighter's energy.",
			"functionCategory": "EnergyBar",
			"functionReturnType": "none",
			"functionCopyPicked": false,
			"functionIsAsync": false,
			"functionParameters": [],
			"eventType": "function-block",
			"conditions": [],
			"actions": [
				{
					"id": "set-default-color",
					"objectClass": "EnergyBar",
					"sid": 723252437902437,
					"parameters": {
						"color": "Fighter(EnergyBar.IID).ColorValue"
					}
				},
				{
					"id": "set-text",
					"objectClass": "EnergyBar",
					"sid": 234005322599237,
					"parameters": {
						"text": "mid( replace( zeropad(0,Fighter(EnergyBar.IID).nEnergyMax), \"0\", ( EnergyBar.IID = 0 ? \"^\" : \" \" ) ) & replace( zeropad(0,Fighter(EnergyBar.IID).nEnergyMax), \"0\", ( EnergyBar.IID = 0 ? \" \" : \"^\" ) ), ( EnergyBar.IID = 0 ? Fighter(EnergyBar.IID).nEnergyMax - Fighter(EnergyBar.IID).nEnergy : Fighter(EnergyBar.IID).nEnergy ), Fighter(EnergyBar.IID).nEnergyMax )"
					}
				}
			],
			"sid": 113711322765195
		}
	],
	"sid": 744869350564622
}